{
    "name": "Explorer les ressources",
    "url": "https://www.bibliotheques.universite-paris-saclay.fr/explorer-les-ressources",
    "hours": "Horaires non disponibles",
    "address": "Adresse non disponible",
    "contact": "Contact non disponible",
    "services": [
        "Explorer les ressources",
        "Chercher un document",
        "Ressources 24h/24",
        "Lean Library Access",
        "Accès aux abonnements via Google Scholar",
        "Rechercher un mémoire, une thèse",
        "Accéder aux annales d'examens",
        "Bibliothèque numérique Numaclay"
    ],
    "description": "# Explorer les ressources | Bibliothèques\n\n## Contenu principal (texte brut)\nAccueil Explorer les ressources Explorer les ressources Imprimer cet article Partager Twitter Facebook Linkedin Par mail Chercher un document Toutes les ressources 24h/24 L'extension de navigateur Library Access Paramétrer Google Scholar Chercher une thèse, un mémoire Accéder aux annales d'examens\n\n## Sections structurées\n### Explorer les ressources\n\n#### Chercher un document\n\n#### Toutes les ressources 24h/24\n\n#### L'extension de navigateur Library Access\n\n#### Paramétrer Google Scholar\n\n#### Chercher une thèse, un mémoire\n\n#### Accéder aux annales d'examens\n\n## Listes\n* Accueil\n* Explorer les ressources\n* Twitter\n* Facebook\n* Linkedin\n* Par mail\n* Twitter\n* Facebook\n* Linkedin\n* Par mail\n\n## Liens importants\n* [Accueil](/)\n* [Twitter](https://twitter.com/intent/tweet/?url=http%3A//www.bibliotheques.universite-paris-saclay.fr/explorer-les-ressources&text=Explorer%20les%20ressources)\n* [Facebook](https://www.facebook.com/sharer/sharer.php?u=http%3A//www.bibliotheques.universite-paris-saclay.fr/explorer-les-ressources)\n* [Linkedin](https://www.linkedin.com/shareArticle?mini=true&url=http%3A//www.bibliotheques.universite-paris-saclay.fr/explorer-les-ressources&title=Explorer%20les%20ressources)\n* [Chercher un document](/node/267280)\n* [Toutes les ressources 24h/24](/node/191695)\n* [L'extension de navigateur Library Access](/node/253927)\n* [Paramétrer Google Scholar](/node/253975)\n* [Chercher une thèse, un mémoire](/node/267283)\n* [Accéder aux annales d'examens](/node/267295)\n"
}